{
  "name": "ament_cmake_gtest",
  "version": "2.5.6",
  "description": "The ability to add gtest-based tests in the ament buildsystem in CMake.",
  "license": "Apache License 2.0",
  "build_type": "ament_cmake",
  "deprecated": null,
  "urls": [],
  "repo": {
    "name": "ament_cmake",
    "url": "https://github.com/ament/ament_cmake.git",
    "branch": "jazzy"
  },
  "dependencies": {
    "buildtool": [
      "ament_cmake_core"
    ],
    "buildtool_export": [
      "ament_cmake_test",
      "gtest",
      "gtest_vendor"
    ],
    "depended_on_by": [
      "adi_imu",
      "ament_cmake_auto",
      "ament_cmake_auto",
      "ament_cmake_gen_version_h",
      "ament_cmake_gmock",
      "ament_cmake_ros",
      "ament_index_cpp",
      "angles",
      "apex_test_tools",
      "asio_cmake_module",
      "auto_apms_behavior_tree_core",
      "auto_apms_util",
      "behaviortree_cpp",
      "behaviortree_cpp_v3",
      "camera_calibration_parsers",
      "camera_info_manager",
      "class_loader",
      "cloudini_lib",
      "cm_executors",
      "color_util",
      "compass_conversions",
      "compass_interfaces",
      "compressed_depth_image_transport",
      "cras_cpp_common",
      "crx_kinematics",
      "cv_bridge",
      "data_tamer_cpp",
      "data_tamer_tools",
      "dataspeed_can_msg_filters",
      "dataspeed_can_tools",
      "dataspeed_can_usb",
      "depthimage_to_laserscan",
      "diagnostic_aggregator",
      "diagnostic_remote_logging",
      "diagnostic_updater",
      "ds_dbw_can",
      "easynav_common",
      "easynav_core",
      "easynav_sensors",
      "easynav_system",
      "ecl_command_line",
      "ecl_concepts",
      "ecl_config",
      "ecl_containers",
      "ecl_converters",
      "ecl_converters_lite",
      "ecl_devices",
      "ecl_filesystem",
      "ecl_geometry",
      "ecl_ipc",
      "ecl_linear_algebra",
      "ecl_manipulators",
      "ecl_math",
      "ecl_mobile_robot",
      "ecl_mpl",
      "ecl_sigslots",
      "ecl_statistics",
      "ecl_streams",
      "ecl_threads",
      "ecl_time",
      "ecl_type_traits",
      "ecl_utilities",
      "etsi_its_msgs_utils",
      "event_camera_codecs",
      "fastcdr",
      "ffmpeg_encoder_decoder",
      "ffmpeg_image_transport",
      "ffmpeg_image_transport_tools",
      "filters",
      "fkie_message_filters",
      "flex_sync",
      "fmi_adapter",
      "foxglove_compressed_video_transport",
      "fuse_constraints",
      "fuse_core",
      "fuse_graphs",
      "fuse_loss",
      "fuse_models",
      "fuse_optimizers",
      "fuse_publishers",
      "fuse_variables",
      "fusioncore_core",
      "geographic_msgs",
      "geometric_shapes",
      "grid_map_core",
      "grid_map_costmap_2d",
      "grid_map_cv",
      "grid_map_demos",
      "grid_map_filters",
      "grid_map_loader",
      "grid_map_octomap",
      "grid_map_pcl",
      "grid_map_ros",
      "grid_map_sdf",
      "grid_map_visualization",
      "gscam",
      "hri",
      "image_geometry",
      "image_transport",
      "imu_filter_madgwick",
      "interactive_markers",
      "io_context",
      "kdl_inverse_dynamics_solver",
      "kdl_parser",
      "laser_filters",
      "laser_geometry",
      "laser_segmentation",
      "libmavconn",
      "libstatistics_collector",
      "libyaml_vendor",
      "lttngpy",
      "magnetic_model",
      "magnetometer_compass",
      "magnetometer_pipeline",
      "mavros",
      "mavros_extras",
      "mbf_abstract_nav",
      "message_filters",
      "micro_ros_diagnostic_bridge",
      "mola_bridge_ros2",
      "mola_common",
      "mola_demos",
      "mola_launcher",
      "mola_lidar_odometry",
      "mola_lidar_odometry",
      "mola_metric_maps",
      "mola_state_estimation_smoother",
      "mola_test_datasets",
      "moveit_core",
      "moveit_kinematics",
      "mrpt_pf_localization",
      "mujoco_ros2_control",
      "mujoco_ros2_control_plugins",
      "mvsim",
      "nao_lola",
      "nao_lola_client",
      "naoqi_libqi",
      "nav2_behavior_tree",
      "nav2_behaviors",
      "nav2_bringup",
      "nav2_collision_monitor",
      "nav2_constrained_smoother",
      "nav2_controller",
      "nav2_core",
      "nav2_costmap_2d",
      "nav2_graceful_controller",
      "nav2_lifecycle_manager",
      "nav2_map_server",
      "nav2_mppi_controller",
      "nav2_navfn_planner",
      "nav2_regulated_pure_pursuit_controller",
      "nav2_rotation_shim_controller",
      "nav2_route",
      "nav2_smac_planner",
      "nav2_smoother",
      "nav2_system_tests",
      "nav2_theta_star_planner",
      "nav2_util",
      "nav2_velocity_smoother",
      "nav2_voxel_grid",
      "nav2_waypoint_follower",
      "navmap_core",
      "navmap_examples",
      "novatel_gps_driver",
      "octomap_ros",
      "off_highway_can",
      "open3d_conversions",
      "pal_statistics",
      "parameter_expression",
      "parameter_traits",
      "pcl_conversions",
      "pcl_ros",
      "performance_test",
      "plansys2_bt_actions",
      "plansys2_core",
      "plansys2_domain_expert",
      "plansys2_executor",
      "plansys2_lifecycle_manager",
      "plansys2_pddl_parser",
      "plansys2_planner",
      "plansys2_popf_plan_solver",
      "plansys2_problem_expert",
      "plansys2_terminal",
      "plansys2_tests",
      "plansys2_tools",
      "play_motion2",
      "play_motion_builder",
      "plotjuggler_msgs",
      "pluginlib",
      "point_cloud_msg_wrapper",
      "pose_cov_ops",
      "qml6_ros2_plugin",
      "qml_ros2_plugin",
      "quaternion_operation",
      "rcl",
      "rcl_action",
      "rcl_lifecycle",
      "rcl_logging_noop",
      "rcl_logging_rcutils",
      "rcl_yaml_param_parser",
      "rclc",
      "rclc_lifecycle",
      "rclc_parameter",
      "rclcpp",
      "rclcpp_action",
      "rclcpp_cascade_lifecycle",
      "rclcpp_components",
      "rclcpp_lifecycle",
      "rclpy",
      "rcpputils",
      "rcss3d_agent",
      "rcss3d_nao",
      "rcutils",
      "realsense2_camera",
      "resource_retriever",
      "rmw_fastrtps_cpp",
      "rmw_fastrtps_dynamic_cpp",
      "rmw_implementation",
      "roadmap_explorer",
      "robot_calibration",
      "robot_localization",
      "robot_state_publisher",
      "ros1_bridge",
      "ros2_fmt_logger",
      "ros2_socketcan",
      "ros_babel_fish",
      "ros_core",
      "ros_gz_bridge",
      "ros_image_to_qimage",
      "rosbag2_storage",
      "rosbot_hardware_interfaces",
      "rosidl_generator_rs",
      "rosidl_runtime_c",
      "rosidl_runtime_cpp",
      "rosidl_typesupport_fastrtps_c",
      "rosidl_typesupport_fastrtps_cpp",
      "rosidl_typesupport_interface",
      "rqt_image_overlay",
      "rttest",
      "rviz_common",
      "rviz_default_plugins",
      "rviz_rendering",
      "rviz_rendering_tests",
      "rviz_satellite",
      "rviz_visual_testing_framework",
      "rviz_visual_tools",
      "sdformat_urdf",
      "self_test",
      "sensor_msgs",
      "serial_driver",
      "sicks300_ros2",
      "simple_actions",
      "simple_grasping",
      "slam_toolbox",
      "slg_msgs",
      "srdfdom",
      "swri_geometry_util",
      "swri_image_util",
      "swri_math_util",
      "swri_roscpp",
      "swri_transform_util",
      "synapticon_ros2_control",
      "system_modes",
      "system_modes_examples",
      "tcb_span",
      "test_msgs",
      "tf2",
      "tf2_2d",
      "tf2_bullet",
      "tf2_eigen",
      "tf2_eigen_kdl",
      "tf2_geometry_msgs",
      "tf2_kdl",
      "tf2_ros",
      "tf2_sensor_msgs",
      "tlsf_cpp",
      "topic_tools",
      "tracetools",
      "trimble_driver",
      "tuw_airskin_msgs",
      "tuw_geo_msgs",
      "tuw_geometry",
      "tuw_geometry_msgs",
      "tuw_graph_msgs",
      "tuw_msgs",
      "tuw_multi_robot_msgs",
      "tuw_nav_msgs",
      "tuw_object_map_msgs",
      "tuw_object_msgs",
      "tuw_std_msgs",
      "udp_driver",
      "ur10_inverse_dynamics_solver",
      "ur_calibration",
      "usb_cam",
      "vector_pursuit_controller",
      "velodyne_driver",
      "velodyne_pointcloud",
      "vision_msgs",
      "warehouse_ros_sqlite",
      "wiimote",
      "yaets",
      "yasmin",
      "yasmin_factory",
      "yasmin_ros"
    ]
  },
  "messages": {},
  "services": {},
  "actions": {}
}
